hugchat/__init__.py
hugchat/cli.py
hugchat/exceptions.py
hugchat/hugchat.py
hugchat/login.py
hugchat/message.py
hugchat/types/assistant.py
hugchat/types/file.py
hugchat/types/message.py
hugchat/types/model.py
hugchat/types/tool.py
hugchats-0.4.9.dist-info/LICENSE
hugchats-0.4.9.dist-info/METADATA
hugchats-0.4.9.dist-info/WHEEL
hugchats-0.4.9.dist-info/top_level.txt
hugchats-0.4.9.dist-info/RECORD
