Metadata-Version: 2.1
Name: hugchats
Version: 0.4.9
Summary: A huggingchat python api.
Home-page: https://github.com/Soulter/hugging-chat-api
Author: adfboba
Author-email: adfboba@gmail.com
License: GNU Affero General Public License v3.0
Project-URL: Bug Report, https://github.com/Soulter/hugging-chat-api/issues
Classifier: License :: OSI Approved :: GNU General Public License v3 (GPLv3)
Classifier: Intended Audience :: Developers
Classifier: Intended Audience :: End Users/Desktop
Classifier: Natural Language :: English
Classifier: Topic :: Software Development :: Libraries :: Python Modules
Classifier: Programming Language :: Python :: 3 :: Only
Classifier: Programming Language :: Python :: 3.6
Classifier: Programming Language :: Python :: 3.7
Classifier: Programming Language :: Python :: 3.8
Classifier: Programming Language :: Python :: 3.9
Classifier: Programming Language :: Python :: 3.10
Classifier: Programming Language :: Python :: 3.11
License-File: LICENSE
Requires-Dist: requests
Requires-Dist: requests-toolbelt
